arranger/__init__.py
arranger/addon.py
arranger/arranger.py
arranger/colors.py
arranger/options.py
arranger/patterns.py
arranger/server.py
arranger/commander/__init__.py
arranger/commander/parts.py
arranger/commander/selector.py
arranger/commander/store.py
arranger/static/.babelrc
arranger/static/.eslintignore
arranger/static/.eslintrc.cjs
arranger/static/index.ejs
arranger/static/package-lock.json
arranger/static/package.json
arranger/static/tsconfig.json
arranger/static/webpack.conf.js
arranger/static/webpack.config.ts
arranger/static/css/app.css
arranger/static/dist/prod/index.html
arranger/static/dist/prod/static/app.6940a63ceebec410a928.js
arranger/static/dist/prod/static/app.837392354eb3b3e530d7.js
arranger/static/dist/prod/static/css/f0169455e3ffdf6af67ff2060cfc204a.css
arranger/static/dist/prod/static/icons/49adc96483bae6799889b54e4439c901.ico
arranger/static/dist/prod/static/images/02848944bf44761760b4f5bdfab5b034.png
arranger/static/dist/prod/static/images/0a23b519d8de45d427d1163b020fbea4.png
arranger/static/dist/prod/static/images/15661d92432518477038292c354ce8e4.png
arranger/static/dist/prod/static/images/b08a5d369a23c73c9cf770d837f76536.png
arranger/static/dist/prod/static/images/faf9874c1b849437de43e40411881dc0.png
arranger/static/dist/prod/static/manifest/1c337fa2fa1515591f8db20865e618de.webmanifest
arranger/static/ico/android-chrome-192x192.png
arranger/static/ico/android-chrome-512x512.png
arranger/static/ico/apple-touch-icon.png
arranger/static/ico/favicon-16x16.png
arranger/static/ico/favicon-32x32.png
arranger/static/ico/favicon.ico
arranger/static/ico/site.webmanifest
arranger/static/js/index.js
arranger/static/js/page.js
arranger/static/js/parts.js
arranger/static/js/state.js
arranger/static/js/store.js
arranger/static/js/wsclient.js
lifx_photons_arranger-0.9.3.dist-info/METADATA
lifx_photons_arranger-0.9.3.dist-info/WHEEL
lifx_photons_arranger-0.9.3.dist-info/entry_points.txt
lifx_photons_arranger-0.9.3.dist-info/RECORD
