Metadata-Version: 2.4
Name: lifx-photons-arranger
Version: 0.9.3
Summary: A web interface for changing the user co-ordinates of LIFX tiles
Project-URL: Homepage, http://github.com/delfick/photons/apps/arranger
Author-email: Stephen Moore <github@delfick.com>
License-Expression: MIT
Keywords: arranger,lifx,photons
Requires-Python: >=3.12
Requires-Dist: lifx-photons-core[web-server]>=0.46.4
